fastcap2_core.pypy37-pp73-x86-linux-gnu.so
FastCap2-2.1.dist-info/top_level.txt
FastCap2-2.1.dist-info/RECORD
FastCap2-2.1.dist-info/LICENSE
FastCap2-2.1.dist-info/METADATA
FastCap2-2.1.dist-info/WHEEL
fastcap2/problem.py
fastcap2/surface.py
fastcap2/__init__.py
