Metadata-Version: 2.1
Name: FastCap2
Version: 2.1
Summary: FastCap2 Python port
Home-page: https://klayoutmatthias.github.io/FastCap2/
Author: Matthias Koefferlein
License: UNKNOWN
Platform: UNKNOWN
License-File: LICENSE
